many_requests/__init__.py
many_requests/common.py
many_requests/easy_async.py
many_requests/many_requests_.py
tests/__init__.py
tests/mock_server.py
tests/test_authentication.py
tests/test_easy_async.py
tests/test_many_requests.py
many_requests-0.2.1.dist-info/LICENSE
many_requests-0.2.1.dist-info/METADATA
many_requests-0.2.1.dist-info/WHEEL
many_requests-0.2.1.dist-info/top_level.txt
many_requests-0.2.1.dist-info/RECORD
