Metadata-Version: 2.1
Name: many-requests
Version: 0.2.1
Summary: Dead easy interface for executing many HTTP requests asynchronously. Also provides helper functions for executing embarrassingly parallel async coroutines.
Home-page: https://github.com/joshlk/many_requests
Author: Josh Levy-Kramer
License: MIT License
Project-URL: Documentation, https://joshlk.github.io/many_requests
Project-URL: Code, https://github.com/joshlk/many_requests
Project-URL: Issue tracker, https://github.com/joshlk/many_requests/issues
Platform: UNKNOWN
Classifier: Development Status :: 5 - Production/Stable
Classifier: Intended Audience :: Developers
Classifier: Topic :: Internet :: WWW/HTTP
Classifier: License :: OSI Approved :: MIT License
Classifier: Programming Language :: Python :: 3
Requires-Python: >=3.6
Requires-Dist: trio
Requires-Dist: asks
Requires-Dist: tqdm
Provides-Extra: dev
Requires-Dist: pytest ; extra == 'dev'
Requires-Dist: wheel ; extra == 'dev'
Requires-Dist: setuptools ; extra == 'dev'
Requires-Dist: twine ; extra == 'dev'
Requires-Dist: sphinx (>=3.2.1) ; extra == 'dev'
Requires-Dist: codecov ; extra == 'dev'
Requires-Dist: recommonmark ; extra == 'dev'
Requires-Dist: sphinx-rtd-theme ; extra == 'dev'
Requires-Dist: bump2version ; extra == 'dev'
Requires-Dist: aiohttp ; extra == 'dev'
Requires-Dist: requests ; extra == 'dev'
Requires-Dist: aiohttp-basicauth-middleware ; extra == 'dev'
Provides-Extra: docs
Requires-Dist: sphinx ; extra == 'docs'
Requires-Dist: sphinx-rtd-theme ; extra == 'docs'
